dojo_referee/__init__.py
dojo_referee/__main__.py
dojo_referee/logging.conf
dojo_referee/settings.py
dojo_referee/sound.py
dojo_referee/assets/begin.wav
dojo_referee/assets/finish.wav
dojo_referee-0.1.0.dist-info/METADATA
dojo_referee-0.1.0.dist-info/RECORD
dojo_referee-0.1.0.dist-info/WHEEL
dojo_referee-0.1.0.dist-info/entry_points.txt
dojo_referee-0.1.0.dist-info/top_level.txt
